{
  "packet_id": "FP-P2D-253",
  "case_id": "series_str_split_count_basic_strict",
  "mode": "strict",
  "operation": "series_str_split_count",
  "fixture_provenance": {
    "pandas_version": "2.2.3",
    "oracle_script_sha256": "f38b2fca36d3f10acdeb5fb41213653c2250ca347046ceaea93ef3d4926f4919",
    "generated_at": "2026-04-22T21:02:48Z"
  },
  "str_split_pat": ",",
  "left": {
    "name": "text",
    "index": [
      { "kind": "int64", "value": 0 },
      { "kind": "int64", "value": 1 },
      { "kind": "int64", "value": 2 }
    ],
    "values": [
      { "kind": "utf8", "value": "a,b,c" },
      { "kind": "utf8", "value": "hello" },
      { "kind": "utf8", "value": "x,y,z,w" }
    ]
  },
  "expected_series": {
    "index": [
      { "kind": "int64", "value": 0 },
      { "kind": "int64", "value": 1 },
      { "kind": "int64", "value": 2 }
    ],
    "values": [
      { "kind": "int64", "value": 3 },
      { "kind": "int64", "value": 1 },
      { "kind": "int64", "value": 4 }
    ]
  }
}
