{
  "packet_id": "FP-P2D-221",
  "case_id": "series_str_removesuffix_basic_strict",
  "mode": "strict",
  "operation": "series_str_removesuffix",
  "fixture_provenance": {
    "pandas_version": "2.2.3",
    "oracle_script_sha256": "f38b2fca36d3f10acdeb5fb41213653c2250ca347046ceaea93ef3d4926f4919",
    "generated_at": "2026-04-22T21:02:48Z"
  },
  "str_suffix": ".txt",
  "left": {
    "name": "text",
    "index": [
      { "kind": "int64", "value": 0 },
      { "kind": "int64", "value": 1 },
      { "kind": "int64", "value": 2 }
    ],
    "values": [
      { "kind": "str", "value": "file.txt" },
      { "kind": "str", "value": "data.txt" },
      { "kind": "str", "value": "image.png" }
    ]
  },
  "expected_series": {
    "index": [
      { "kind": "int64", "value": 0 },
      { "kind": "int64", "value": 1 },
      { "kind": "int64", "value": 2 }
    ],
    "values": [
      { "kind": "str", "value": "file" },
      { "kind": "str", "value": "data" },
      { "kind": "str", "value": "image.png" }
    ]
  }
}
